odoo/addons/gestion_editorial/__init__.py
odoo/addons/gestion_editorial/__manifest__.py
odoo/addons/gestion_editorial/hooks.py
odoo/addons/gestion_editorial/data/ddaa_data.xml
odoo/addons/gestion_editorial/data/deposito_compra_data.xml
odoo/addons/gestion_editorial/data/deposito_venta_data.xml
odoo/addons/gestion_editorial/data/promocion_data.xml
odoo/addons/gestion_editorial/i18n_extra/es.po
odoo/addons/gestion_editorial/models/__init__.py
odoo/addons/gestion_editorial/models/liquidacion_descontrol.py
odoo/addons/gestion_editorial/models/pos_order_descontrol.py
odoo/addons/gestion_editorial/models/product_descontrol.py
odoo/addons/gestion_editorial/models/product_pricelist_descontrol.py
odoo/addons/gestion_editorial/models/purchase_order_descontrol.py
odoo/addons/gestion_editorial/models/res_company_descontrol.py
odoo/addons/gestion_editorial/models/res_config_settings_descontrol.py
odoo/addons/gestion_editorial/models/res_partner_descontrol.py
odoo/addons/gestion_editorial/models/sale_order_descontrol.py
odoo/addons/gestion_editorial/models/stock_picking_descontrol.py
odoo/addons/gestion_editorial/static/description/icon.png
odoo/addons/gestion_editorial/static/description/logo-devcontrol.png
odoo/addons/gestion_editorial/static/src/js/sale_order_widget.js
odoo/addons/gestion_editorial/static/src/xml/sale_order_widget.xml
odoo/addons/gestion_editorial/views/liquidacion_descontrol_view.xml
odoo/addons/gestion_editorial/views/product_descontrol_view.xml
odoo/addons/gestion_editorial/views/product_pricelist_descontrol_view.xml
odoo/addons/gestion_editorial/views/purchase_order_descontrol_view.xml
odoo/addons/gestion_editorial/views/report_invoice_document_descontrol_view.xml
odoo/addons/gestion_editorial/views/report_saleorder_document_descontrol_view.xml
odoo/addons/gestion_editorial/views/res_config_settings_descontrol_view.xml
odoo/addons/gestion_editorial/views/res_partner_descontrol_view.xml
odoo/addons/gestion_editorial/views/sale_order_descontrol_view.xml
odoo13_addon_gestion_editorial-13.0.0.7.0.dist-info/METADATA
odoo13_addon_gestion_editorial-13.0.0.7.0.dist-info/WHEEL
odoo13_addon_gestion_editorial-13.0.0.7.0.dist-info/top_level.txt
odoo13_addon_gestion_editorial-13.0.0.7.0.dist-info/RECORD
