Metadata-Version: 2.1
Name: odoo13-addon-gestion_editorial
Version: 13.0.0.7.0
Requires-Python: >=3.5
Requires-Dist: odoo13-addon-account_invoice_pricelist
Requires-Dist: odoo>=13.0a,<13.1dev
Summary: =?utf-8?q?M=C3=B3dulo_para_gesti=C3=B3n_de_la_editorial_Descontrol=2E?=
Home-page: https://framagit.org/devcontrol
License: OPL-1
Author: Colectivo DEVCONTROL
Classifier: Programming Language :: Python
Classifier: Framework :: Odoo
Classifier: Framework :: Odoo :: 13.0
